<?xml version = '1.0' encoding = 'UTF-8'?>
<Relation class="oracle.dbtools.crest.model.design.logical.Relation" name="Relation_5" directorySegmentName="seg_0" id="655448D0-77F1-8DD7-76C3-91A96D387BE0">
<createdBy>SEBASTIAN JIMENEZ</createdBy>
<createdTime>2018-11-19 09:59:21 UTC</createdTime>
<ownerDesignName>Bancos</ownerDesignName>
<engineerTo>
<item key="8A6E1603-C80D-294B-9C5A-4D9512E8B6F5" value="true"/>
</engineerTo>
<sourcePk>51FF86E9-43A7-958D-642A-4DB65E2767E9</sourcePk>
<identifying>false</identifying>
<optionalSource>true</optionalSource>
<optionalTarget>false</optionalTarget>
<sourceCardinality>1</sourceCardinality>
<sourceEntity>120FE997-AA2C-1969-C155-5DCFF06E5C0A</sourceEntity>
<targetCardinalityString>*</targetCardinalityString>
<targetEntity>D2EB33A4-7135-A3E1-F4F4-2C3630824AF0</targetEntity>
<transferable>true</transferable>
<deleteRule>NO ACTION</deleteRule>
</Relation>